catalystcoop.dbfread-3.0.0.data/scripts/dbf2sqlite
dbfread/__init__.py
dbfread/codepages.py
dbfread/dbf.py
dbfread/dbversions.py
dbfread/deprecated_dbf.py
dbfread/exceptions.py
dbfread/field_parser.py
dbfread/ifiles.py
dbfread/memo.py
dbfread/struct_parser.py
dbfread/version.py
catalystcoop.dbfread-3.0.0.dist-info/LICENSE
catalystcoop.dbfread-3.0.0.dist-info/METADATA
catalystcoop.dbfread-3.0.0.dist-info/WHEEL
catalystcoop.dbfread-3.0.0.dist-info/top_level.txt
catalystcoop.dbfread-3.0.0.dist-info/zip-safe
catalystcoop.dbfread-3.0.0.dist-info/RECORD
