Metadata-Version: 2.1
Name: catalystcoop.dbfread
Version: 3.0.0
Summary: Read DBF Files with Python
Home-page: https://github.com/catalyst-cooperative/dbfread
Author: Ole Martin Bjorndalen
Author-email: ombdalen@gmail.com
Maintainer: Zane A. Selvans
Maintainer-email: zane.selvans@catalyst.coop
License: MIT
Project-URL: Source, https://github.com/catalyst-cooperative/dbfread
Project-URL: Issue Tracker, https://github.com/catalyst-cooperative/dbfread/issues
Platform: UNKNOWN
Classifier: Development Status :: 5 - Production/Stable
Classifier: Intended Audience :: Developers
Classifier: Natural Language :: English
Classifier: License :: OSI Approved :: MIT License
Classifier: Programming Language :: Python
Classifier: Programming Language :: Python :: 3.6
Classifier: Programming Language :: Python :: 3.7
Classifier: Programming Language :: Python :: 3.8
Requires-Python: >=3.6
Provides-Extra: doc
Requires-Dist: sphinx (>=3.0) ; extra == 'doc'
Requires-Dist: sphinx-rtd-theme ; extra == 'doc'
Provides-Extra: test
Requires-Dist: coverage ; extra == 'test'
Requires-Dist: pytest ; extra == 'test'
Requires-Dist: pytest-cov ; extra == 'test'
Requires-Dist: zipp ; extra == 'test'
